LICENSE
MANIFEST.in
README.md
crumb.py
setup.py
crumb.py.egg-info/PKG-INFO
crumb.py.egg-info/SOURCES.txt
crumb.py.egg-info/dependency_links.txt
crumb.py.egg-info/top_level.txt